pydark/__init__.py
pydark/chart/__init__.py
pydark/chart/apexcharts.py
pydark/date/__init__.py
pydark/date/dtget.py
pydark/date/dtmath.py
pydark/math/__init__.py
pydark/math/statistic.py
pydark/text/__init__.py
pydark/text/number.py
pydark-0.0.7.dist-info/METADATA
pydark-0.0.7.dist-info/WHEEL
pydark-0.0.7.dist-info/top_level.txt
pydark-0.0.7.dist-info/RECORD
