Metadata-Version: 2.1
Name: pydark
Version: 0.0.7
Summary: DarkPy is a Python library which brings some useful calculations
